replacedateiso/__init__.py
replacedateiso/__main__.py
replacedateiso/base.py
replacedateiso/cli.py
replacedateiso-1.0.1.dist-info/LICENSE
replacedateiso-1.0.1.dist-info/METADATA
replacedateiso-1.0.1.dist-info/WHEEL
replacedateiso-1.0.1.dist-info/entry_points.txt
replacedateiso-1.0.1.dist-info/top_level.txt
replacedateiso-1.0.1.dist-info/RECORD
