Metadata-Version: 2.1
Name: replacedateiso
Version: 1.0.1
Summary: Awesome replacedateiso created by carsten-engelke
Home-page: https://github.com/carsten-engelke/replacedateiso/
Author: carsten-engelke
License-File: LICENSE
Provides-Extra: test
Requires-Dist: pytest ; extra == 'test'
Requires-Dist: coverage ; extra == 'test'
Requires-Dist: flake8 ; extra == 'test'
Requires-Dist: black ; extra == 'test'
Requires-Dist: isort ; extra == 'test'
Requires-Dist: pytest-cov ; extra == 'test'
Requires-Dist: mypy ; extra == 'test'
Requires-Dist: gitchangelog ; extra == 'test'
Requires-Dist: mkdocs ; extra == 'test'
